cueai_architect/__init__.py
cueai_architect/base.py
cueai_architect/ai/__init__.py
cueai_architect/ai/integration/__init__.py
cueai_architect/ai/integration/consciousness_transformer.py
cueai_architect/cognitive/__init__.py
cueai_architect/cognitive/dynamics/__init__.py
cueai_architect/cognitive/dynamics/consciousness_field_simulator.py
cueai_architect/core/__init__.py
cueai_architect/core/foundations/__init__.py
cueai_architect/core/foundations/pre_metric_substrate.py
cueai_architect/rg_flow/__init__.py
cueai_architect/rg_flow/mechanics/__init__.py
cueai_architect/rg_flow/mechanics/rg_flow_integrator.py
cueai_architect/utility/__init__.py
cueai_architect/utility/cue_application_manager.py
cueai_architect-0.1.3.dist-info/METADATA
cueai_architect-0.1.3.dist-info/WHEEL
cueai_architect-0.1.3.dist-info/entry_points.txt
cueai_architect-0.1.3.dist-info/top_level.txt
cueai_architect-0.1.3.dist-info/RECORD
