Metadata-Version: 2.4
Name: cueai-architect
Version: 0.1.3
Summary: Modular AI Architecture Components based on the Collective Unified Equation (CUE) Framework
Author-email: CUE Framework Research Team <cue-research@example.com>
Maintainer-email: Karl Farah Ambrosius <karlambrosius@outlook.com.au>
License: MIT
Project-URL: Homepage, https://github.com/cue-ai-architect/cueai-architect
Project-URL: Documentation, https://cue-ai-architect.readthedocs.io
Project-URL: Repository, https://github.com/cue-ai-architect/cueai-architect.git
Project-URL: Issues, https://github.com/cue-ai-architect/cueai-architect/issues
Keywords: consciousness,quantum,neural-networks,geometric-deep-learning,renormalization-group,fiber-bundles,artificial-intelligence,cue-framework
Classifier: Development Status :: 3 - Alpha
Classifier: Intended Audience :: Science/Research
Classifier: License :: OSI Approved :: MIT License
Classifier: Programming Language :: Python :: 3
Classifier: Programming Language :: Python :: 3.9
Classifier: Programming Language :: Python :: 3.10
Classifier: Programming Language :: Python :: 3.11
Classifier: Programming Language :: Python :: 3.12
Classifier: Topic :: Scientific/Engineering :: Artificial Intelligence
Classifier: Topic :: Scientific/Engineering :: Physics
Classifier: Topic :: Scientific/Engineering :: Mathematics
Requires-Python: >=3.9
Requires-Dist: numpy>=1.21.0
Requires-Dist: scipy>=1.7.0
Requires-Dist: torch>=1.12.0
Requires-Dist: matplotlib>=3.5.0
Requires-Dist: plotly>=5.0.0
Requires-Dist: networkx>=2.6.0
Requires-Dist: sympy>=1.9.0
Requires-Dist: scikit-learn>=1.0.0
Requires-Dist: pandas>=1.3.0
Requires-Dist: tqdm>=4.60.0
Requires-Dist: pydantic>=1.8.0
Requires-Dist: typing-extensions>=4.0.0
Provides-Extra: dev
Requires-Dist: pytest>=6.0.0; extra == "dev"
Requires-Dist: pytest-cov>=3.0.0; extra == "dev"
Requires-Dist: black>=22.0.0; extra == "dev"
Requires-Dist: flake8>=4.0.0; extra == "dev"
Requires-Dist: mypy>=0.900; extra == "dev"
Requires-Dist: pre-commit>=2.15.0; extra == "dev"
Provides-Extra: docs
Requires-Dist: sphinx>=4.0.0; extra == "docs"
Requires-Dist: sphinx-rtd-theme>=1.0.0; extra == "docs"
Requires-Dist: myst-parser>=0.17.0; extra == "docs"
Provides-Extra: experimental
Requires-Dist: qiskit>=0.39.0; extra == "experimental"
Requires-Dist: pennylane>=0.25.0; extra == "experimental"
Requires-Dist: jax>=0.3.0; extra == "experimental"
Requires-Dist: jaxlib>=0.3.0; extra == "experimental"
